modules_for_freethreading.py
modules_for_freethreading-0.3.2.dist-info/METADATA
modules_for_freethreading-0.3.2.dist-info/WHEEL
modules_for_freethreading-0.3.2.dist-info/top_level.txt
modules_for_freethreading-0.3.2.dist-info/RECORD
