Metadata-Version: 2.4
Name: modules_for_freethreading
Version: 0.3.2
Summary: A module to handle module compatibility between free-threading and regular Python builds
Home-page: https://github.com/Locked-chess-official/modules_for_freethreading
Author: Locked-chess-official
Author-email: 13140752715@163.com
Project-URL: Bug Reports, https://github.com/Locked-chess-official/modules_for_freethreading/issues
Project-URL: Source, https://github.com/Locked-chess-official/modules_for_freethreading
Classifier: Programming Language :: Python :: 3
Classifier: License :: OSI Approved :: MIT License
Classifier: Operating System :: OS Independent
Requires-Python: >=3.13
Requires-Dist: packaging>=21.0
Dynamic: author
Dynamic: author-email
Dynamic: classifier
Dynamic: description
Dynamic: description-content-type
Dynamic: home-page
Dynamic: project-url
Dynamic: requires-dist
Dynamic: requires-python
Dynamic: summary
